lkfacedetection/__init__.py
lkfacedetection-0.0.1.dist-info/METADATA
lkfacedetection-0.0.1.dist-info/WHEEL
lkfacedetection-0.0.1.dist-info/top_level.txt
lkfacedetection-0.0.1.dist-info/RECORD
