Metadata-Version: 2.1
Name: lkfacedetection
Version: 0.0.1
Summary: Detect faces using ML models just with few lines of code
Home-page: https://www.lakshaykumar.tech/
Author: Lakshay Kumar
Author-email: contact@lakshaykumar.tech
License: MIT
Platform: UNKNOWN
Classifier: Programming Language :: Python :: 3
Classifier: License :: OSI Approved :: MIT License
Classifier: Operating System :: OS Independent
Requires-Python: >=3.3
Requires-Dist: mediapipe
